gdict/__init__.py
gdict/cli.py
gdict-0.1.1.dist-info/entry_points.txt
gdict-0.1.1.dist-info/WHEEL
gdict-0.1.1.dist-info/METADATA
gdict-0.1.1.dist-info/RECORD
